{
  "id": "monthplanrecruit",
  "handleOnPC": {
    "tasknode": [
      ""
    ],
    "flag": [
      "resubmit"
    ]
  },
  "selectPerson": {
    "tasknode": [
      ""
    ],
    "beforPop": false
  },
  "forms": [
    {
      "title": "基本信息",
      "pageid": "jbxx",
      "component": "panel",
      "subComponents": [
        {
          "title": "申请单号",
          "component": "text",
          "editablenode": "",
          "name": "mainModel.appid"
        },
        {
          "title": "申请日期",
          "component": "date1",
          "editablenode": "",
          "name": "mainModel.appda"
        },
        {
          "title": "申请人姓名",
          "component": "label",
          "editablenode": "",
          "label": [
            "mainModel.pernr",
            "-",
            "mainModel.username"
          ]
        },
        {
          "title": "所属部门",
          "component": "label",
          "editablenode": "",
          "label": [
            "mainModel.sysbusinessunitname",
            "-",
            "mainModel.sysdeptname"
          ]
        },
        {
          "title": "",
          "component": "hidden",
          "name": "mainModel.bukrs"
        },
        {
          "title": "",
          "component": "hidden",
          "name": "mainModel.userid"
        },
        {
          "title": "",
          "component": "hidden",
          "name": "mainModel.username"
        },
        {
          "title": "",
          "component": "hidden",
          "name": "mainModel.pernr"
        },
        {
          "title": "",
          "component": "hidden",
          "name": "mainModel.syspostname"
        },
        {
          "title": "",
          "component": "hidden",
          "name": "mainModel.sysdeptid"
        },
        {
          "title": "",
          "component": "hidden",
          "name": "mainModel.sysdeptname"
        },
        {
          "title": "",
          "component": "hidden",
          "name": "mainModel.sysbusinessunitid"
        },
        {
          "title": "",
          "component": "hidden",
          "name": "mainModel.sysbusinessunitname"
        },
        {
          "title": "",
          "component": "hidden",
          "name": "mainModel.postid"
        },
        {
          "title": "",
          "component": "hidden",
          "name": "mainModel.id"
        }
      ]
    },
    {
      "title": "招聘需求计划信息",
      "pageid": "applyplanInfo",
      "component": "panel",
      "subComponents": [
        {
          "title": "职位名称",
          "component": "text",
          "name": "mainModel.r_postnm"
        },
        {
          "title": "用人部门",
          "component": "text",
          "name": "mainModel.r_usedeptnm"
        },
        {
          "title": "部门领导",
          "component": "text",
          "name": "mainModel.r_leadernm"
        },
        {
          "title": "领导邮箱",
          "component": "text",
          "name": "mainModel.r_email"
        },
        {
          "title": "学历要求",
          "component": "select",
          "name": "mainModel.r_eduid",
          "options":[
            {
              "text": "初中",
              "value": "初中"
            },
            {
              "text": "高中",
              "value": "高中"
            },
            {
              "text": "中技",
              "value": "中技"
            },
            {
              "text": "中专",
              "value": "中专"
            },
            {
              "text": "大专",
              "value": "大专"
            },
            {
              "text": "本科",
              "value": "本科"
            },
            {
              "text": "硕士",
              "value": "硕士"
            },
            {
              "text": "博士",
              "value": "博士"
            },
            {
              "text": "MBA",
              "value": "MBA"
            },
            {
              "text": "EMBA",
              "value": "EMBA"
            },
            {
              "text": "其他",
              "value": "其他"
            }
          ]
        },
        {
          "title": "岗位职责描述",
          "component": "textarea",
          "name": "mainModel.r_duty"
        },
        {
          "title": "专业素质要求",
          "component": "textarea",
          "name": "mainModel.r_profe"
        },
        {
          "title": "其他素质要求",
          "component": "textarea",
          "name": "mainModel.r_request"
        },
        {
          "title": "计划月份",
          "component": "text",
          "name": "mainModel.r_month"
        },
        {
          "title": "招聘数量",
          "component": "text",
          "name": "mainModel.r_num"
        },
        {
          "title": "需求原因",
          "component": "select",
          "name": "mainModel.r_reason",
          "options":[
            {
              "text": "替补",
              "value": "1"
            },
            {
              "text": "空编",
              "value": "2"
            }
          ]
        },
        {
          "title": "期望到岗日期",
          "component": "date1",
          "name": "mainModel.r_indate"
        },
        {
          "title": "是否招聘应届生",
          "component": "select",
          "name": "mainModel.r_isfresh",
          "options":[
            {
              "text": "是",
              "value": "0"
            },
            {
              "text": "否",
              "value": "1"
            }
          ]
        },
        {
          "title": "职位ID",
          "component": "text",
          "name": "mainModel.r_zwid"
        },
        {
          "title": "负责人",
          "component": "select",
          "name": "mainModel.r_fzr",
          "options":[
            {
              "text": "新凤祥",
              "value": "531a24595de62b9d015de8fa9e370001"
            },
            {
              "text": "祥泰国际",
              "value": "531a245961d77c250161e576390c000a"
            },
            {
              "text": "凤翔股份",
              "value": "531a2459621fb6a6016229e95aca0003"
            },
            {
              "text": "祥光集团",
              "value": "531a245961d77c250161e57569150009"
            }
          ]
        },
        {
          "title": "其他招聘角色",
          "component": "text",
          "name": "mainModel.r_otherjs"
        },
        {
          "title": "职能类别",
          "component": "select",
          "name": "mainModel.r_znlb",
          "options":[
            {
              "text": "财务/审计/税务",
              "value": "3"
            },
            {
              "text": "人力资源",
              "value": "2"
            },
            {
              "text": "房地产/建筑/物业",
              "value": "10"
            },
            {
              "text": "高级管理",
              "value": "1"
            },
            {
              "text": "法务",
              "value": "7"
            },
            {
              "text": "销售/客服/技术支持",
              "value": "6"
            },
            {
              "text": "公关/媒介",
              "value": "5"
            },
            {
              "text": "品牌/市场",
              "value": "4"
            },
            {
              "text": "IT/互联网/通信",
              "value": "9"
            },
            {
              "text": "行政/后勤/文秘",
              "value": "8"
            },
            {
              "text": "医疗、护理、生活服务",
              "value": "13"
            },
            {
              "text": "生产/制造",
              "value": "11"
            },
            {
              "text": "采购/贸易/交通物流",
              "value": "12"
            }
          ]
        },
        {
          "title": "工作地点",
          "component": "label",
          "label": [
            "mainModel.r_province",
            "-",
            "mainModel.r_city"
          ]
        },
        {
          "title": "薪资范围",
          "component": "text",
          "name": "mainModel.r_rangenm"
        },
        {
          "title": "开始时间",
          "component": "date1",
          "name": "mainModel.r_sdate"
        },
        {
          "title": "工作年限",
          "component": "text",
          "name": "mainModel.r_years"
        },
        {
          "title": "保密职位",
          "component": "select",
          "name": "mainModel.r_secret",
          "options":[
            {
              "text": "是",
              "value": "1"
            },
            {
              "text": "否",
              "value": "0"
            }
          ]
        },
        {
          "title": "职位类型",
          "component": "text",
          "name": "mainModel.r_zntypenm"
        },
        {
          "title": "是否需要印制名片",
          "component": "select",
          "id": "sfyzmp",
          "name": "mainModel.sfyzmp",
          "options":[
            {
              "text": "是",
              "value": "0"
            },
            {
              "text": "否",
              "value": "1"
            }
          ]
        },
        {
          "title": "印制数量",
          "component": "text",
          "name": "mainModel.yznum",
          "showLinkage": [
            {
              "id": "sfyzmp",
              "values": [
                "是"
              ]
            }
          ]
        },
        {
          "title": "对外职务",
          "component": "text",
          "name": "mainModel.dwzw",
          "showLinkage": [
            {
              "id": "sfyzmp",
              "values": [
                "是"
              ]
            }
          ]
        }
      ]
    }
  ]
}
