{
  "id": "flow_gmkoa_tenderask",
  "handleOnPC": {
    "tasknode": [
      ""
    ],
    "flag": [
      "resubmit"
    ]
  },
  "selectPerson": {
    "tasknode": [
      ""
    ],
    "beforPop": false
  },
  "forms": [
    {
      "title": "申请信息",
      "pageid": "sqxx",
      "component": "panel",
      "subComponents": [
        {
          "title": "申请单号",
          "component": "text",
          "editablenode": "",
          "name": "mainModel.appid"
        },
        {
          "title": "申请日期",
          "component": "date1",
          "editablenode": "",
          "name": "mainModel.appda"
        },
        {
          "title": "申请人姓名",
          "component": "label",
          "editablenode": "",
          "label": [
            "mainModel.pernr",
            "-",
            "mainModel.username"
          ]
        },
        {
          "title": "所属部门",
          "component": "label",
          "editablenode": "",
          "label": [
            "mainModel.sysbusinessunitname",
            "-",
            "mainModel.sysdeptname"
          ]
        },
        {
          "title": "",
          "component": "hidden",
          "name": "mainModel.bukrs"
        },
        {
          "title": "",
          "component": "hidden",
          "name": "mainModel.userid"
        },
        {
          "title": "",
          "component": "hidden",
          "name": "mainModel.username"
        },
        {
          "title": "",
          "component": "hidden",
          "name": "mainModel.pernr"
        },
        {
          "title": "",
          "component": "hidden",
          "name": "mainModel.syspostname"
        },
        {
          "title": "",
          "component": "hidden",
          "name": "mainModel.sysdeptid"
        },
        {
          "title": "",
          "component": "hidden",
          "name": "mainModel.sysdeptname"
        },
        {
          "title": "",
          "component": "hidden",
          "name": "mainModel.sysbusinessunitid"
        },
        {
          "title": "",
          "component": "hidden",
          "name": "mainModel.sysbusinessunitname"
        },
        {
          "title": "",
          "component": "hidden",
          "name": "mainModel.postid"
        },
        {
          "title": "",
          "component": "hidden",
          "name": "mainModel.id"
        }
      ]
    },
    {
      "title": "初始信息",
      "pageid": "sqInfo",
      "component": "panel",
      "subComponents": [
        {
          "title": "标的物名称",
          "component": "text",
          "name": "mainModel.subjtMatter"
        },
        {
          "title": "公司",
          "component": "text",
          "name": "mainModel.cdbutxt"
        },
        {
          "title": "业务类型",
          "component": "text",
          "name": "mainModel.grantMoldtxt"
        },
        {
          "title": "标的金额(原币)",
          "component": "text",
          "name": "mainModel.subjtYamout"
        },
        {
          "title": "币种",
          "component": "text",
          "name": "mainModel.currencyidtxt"
        },
        {
          "title": "汇率",
          "component": "text",
          "name": "mainModel.exchgeRate"
        },
        {
          "title": "标的金额",
          "component": "text",
          "name": "mainModel.subjtAmout"
        },
        {
          "title": "金额大写",
          "component": "text",
          "name": "mainModel.chinaNumber"
        },
        {
          "title": "买卖",
          "component": "radio",
          "name": "mainModel.dealType",
          "options": [
            {
              "title": "采购",
              "value": "采购"
            },
            {
              "title": "销售",
              "value": "销售"
            }
          ]
        },
        {
          "title": "招标形式",
          "component": "radio",
          "name": "mainModel.tendMode",
          "options": [
            {
              "title": "招标",
              "value": "0"
            },
            {
              "title": "议标",
              "value": "1"
            }
          ]
        },
        {
          "title": "标的物用途",
          "component": "text",
          "name": "mainModel.forGoal"
        }
      ]
    },
    {
      "title": "招标要求",
      "pageid": "requestInfo",
      "component": "panel",
      "subComponents": [
        {
          "title": "标书编制",
          "component": "radio",
          "name": "mainModel.bidDoc",
          "options": [
            {
              "title": "编制标书",
              "value": "0"
            },
            {
              "title": "不编制标书",
              "value": "1"
            }
          ]
        },
        {
          "title": "招标时间",
          "component": "text",
          "datatype": "date",
          "dateFormat": "yyyy-MM-dd",
          "name": "mainModel.tenderTime"
        },
        {
          "title": "报价方式",
          "component": "text",
          "name": "mainModel.offerType"
        },
        {
          "title": "评标方式",
          "component": "text",
          "name": "mainModel.bidType"
        },
        {
          "title": "招标部门负责人",
          "component": "textarea",
          "name": "mainModel.tderMemberpst"
        },
        {
          "title": "主要抄送人",
          "component": "textarea",
          "name": "mainModel.notifierstxt"
        },
        {
          "title": "招标地点",
          "component": "textarea",
          "name": "mainModel.tenderSite"
        },
        {
          "title": "投标人的资质",
          "component": "textarea",
          "name": "mainModel.aptitude"
        },
        {
          "title": "技术要求",
          "component": "textarea",
          "name": "mainModel.techRequt"
        },
        {
          "title": "保证金要求",
          "component": "textarea",
          "name": "mainModel.deposit"
        },
        {
          "title": "其他",
          "component": "textarea",
          "name": "mainModel.others"
        }
      ]
    },
    {
      "title": "投标者信息",
      "pageid": "bidderInfo",
      "component": "panel",
      "subComponents": [
        {
          "component": "table_form",
          "titleIndex": 0,
          "id": "bidder_table",
          "basePath": "tenderchlds",
          "tableForms": [
            {
              "title": "投标者",
              "component": "text",
              "name": "tenders"
            },
            {
              "title": "描述",
              "component": "text",
              "name": "remark"
            },
            {
              "title": "传真",
              "component": "text",
              "name": "faxid"
            },
            {
              "title": "电话",
              "component": "text",
              "name": "fixphone"
            },
            {
              "title": "邮箱",
              "component": "text",
              "name": "mailid"
            },
            {
              "title": "其他",
              "component": "text",
              "name": "others"
            }
          ]
        }
      ]
    }
  ]
}

