{
  "id": "flow_gmkoa_tenderresult",
  "handleOnPC": {
    "tasknode": [
      ""
    ],
    "flag": [
      "resubmit"
    ]
  },
  "selectPerson": {
    "tasknode": [
      ""
    ],
    "beforPop": false
  },
  "forms": [
    {
      "title": "申请人信息",
      "pageid": "sqxx",
      "component": "panel",
      "subComponents": [
        {
          "title": "申请单号",
          "component": "text",
          "editablenode": "",
          "name": "mainModel.appid"
        },
        {
          "title": "申请日期",
          "component": "date1",
          "editablenode": "",
          "name": "mainModel.appda"
        },
        {
          "title": "申请人姓名",
          "component": "label",
          "editablenode": "",
          "label": [
            "mainModel.pernr",
            "-",
            "mainModel.username"
          ]
        },
        {
          "title": "所属部门",
          "component": "label",
          "editablenode": "",
          "label": [
            "mainModel.sysbusinessunitname",
            "-",
            "mainModel.sysdeptname"
          ]
        },
        {
          "title": "",
          "component": "hidden",
          "name": "mainModel.bukrs"
        },
        {
          "title": "",
          "component": "hidden",
          "name": "mainModel.userid"
        },
        {
          "title": "",
          "component": "hidden",
          "name": "mainModel.username"
        },
        {
          "title": "",
          "component": "hidden",
          "name": "mainModel.pernr"
        },
        {
          "title": "",
          "component": "hidden",
          "name": "mainModel.syspostname"
        },
        {
          "title": "",
          "component": "hidden",
          "name": "mainModel.sysdeptid"
        },
        {
          "title": "",
          "component": "hidden",
          "name": "mainModel.sysdeptname"
        },
        {
          "title": "",
          "component": "hidden",
          "name": "mainModel.sysbusinessunitid"
        },
        {
          "title": "",
          "component": "hidden",
          "name": "mainModel.sysbusinessunitname"
        },
        {
          "title": "",
          "component": "hidden",
          "name": "mainModel.postid"
        },
        {
          "title": "",
          "component": "hidden",
          "name": "mainModel.id"
        }
      ]
    },
    {
      "title": "申请信息",
      "pageid": "sqInfo",
      "component": "panel",
      "subComponents": [
        {
          "title": "交易类型",
          "component": "radio",
          "id": "trdeid",
          "name": "mainModel.dealType",
          "options": [
            {
              "title": "采购",
              "value": "0"
            },
            {
              "title": "销售",
              "value": "1"
            }
          ]
        },
        {
          "title": "是否最低价",
          "component": "radio",
          "name": "mainModel.floorPrice",
          "options": [
            {
              "title": "是",
              "value": "0"
            },
            {
              "title": "否",
              "value": "1"
            }
          ]
        },
        {
          "title": "招标形式",
          "component": "radio",
          "name": "mainModel.tendMode",
          "options": [
            {
              "title": "招标",
              "value": "0"
            },
            {
              "title": "议标",
              "value": "1"
            }
          ]
        },
        {
          "title": "价格类型",
          "component": "text",
          "name": "mainModel.priceType",
          "showLinkage": [
            {
              "id": "trdeid",
              "values": ["1"]
            }
          ]
        },
        {
          "title": "招标物资分类",
          "component": "text",
          "name": "mainModel.goodsTypetxt",
          "showLinkage": [
            {
              "id": "trdeid",
              "values": ["0"]
            }
          ]
        },
        {
          "title": "采购组织",
          "component": "text",
          "name": "mainModel.purchaOrgtxt",
          "showLinkage": [
            {
              "id": "trdeid",
              "values": ["0"]
            }
          ]
        },
        {
          "title": "付款条件",
          "component": "text",
          "name": "mainModel.termsPaymentxt",
          "showLinkage": [
            {
              "id": "trdeid",
              "values": ["0"]
            }
          ]
        },
        {
          "title": "业务类型",
          "component": "text",
          "name": "mainModel.grantMoldtxt"
        },
        {
          "title": "招标申请单",
          "component": "text",
          "name": "mainModel.tenderNo"
        },
        {
          "title": "需求部门负责人",
          "component": "textarea",
          "name": "mainModel.npnr"
        },
        {
          "title": "服务部门负责人",
          "component": "textarea",
          "name": "mainModel.spnr"
        },
        {
          "title": "过程及意见",
          "component": "textarea",
          "name": "mainModel.remarks"
        }
      ]
    },
    {
      "title": "中标结果",
      "pageid": "childInfo",
      "component": "panel",
      "subComponents": [
        {
          "component": "table_form",
          "titleIndex": 0,
          "id": "child_table",
          "basePath": "resultchilds",
          "tableForms": [
            {
              "title": "资产/物料号",
              "component": "label",
              "label": [
                "assetsId",
                "assetstxt"
              ]
            },
            {
              "title": "供应商/客户",
              "component": "label",
              "label": [
                "supplierId",
                "supplierName"
              ]
            },
            {
              "title": "定价单位",
              "component": "text",
              "name": "per"
            },
            {
              "title": "币种",
              "component": "text",
              "name": "currencyId"
            },
            {
              "title": "数量单位",
              "component": "text",
              "name": "unit"
            },
            {
              "title": "单价",
              "component": "text",
              "name": "price"
            },
            {
              "title": "开始日期",
              "component": "text",
              "name": "bDate"
            },
            {
              "title": "结束日期",
              "component": "text",
              "name": "eDate"
            },
            {
              "title": "SAP返回状态",
              "component": "text",
              "name": "returnsval"
            }
          ]
        }
      ]
    }
  ]
}

