{
  "id": "xtgj_staffemploy",
  "handleOnPC": {
    "tasknode": [
      
    ],
    "flag": [
      "resubmit"
    ]
  },
  "selectPerson": {
    "tasknode": [
      
    ],
    "beforPop": false
  },
  "pageSelectIndex": {
    "defaultIndex": 0,
    "selectIndexArray": [
      {
        "selectIndex": 0,
        "tasknode": [

        ]
      }
    ]
  },
  "forms": [
    {
      "title": "基本信息",
      "pageid": "jbxx",
      "component": "panel",
      "subComponents": [
        {
          "title": "申请单号",
          "component": "text",
          "editablenode": "",
          "name": "mainModel.appid"
        },
        {
          "title": "申请日期",
          "component": "date1",
          "editablenode": "",
          "name": "mainModel.appda"
        },
        {
          "title": "申请人姓名",
          "component": "label",
          "editablenode": "",
          "label": [
            "mainModel.pernr",
            "-",
            "mainModel.username"
          ]
        },
        {
          "title": "所属部门",
          "component": "label",
          "editablenode": "",
          "label": [
            "mainModel.sysbusinessunitname",
            "-",
            "mainModel.sysdeptname"
          ]
        },
        {
          "title": "",
          "component": "hidden",
          "name": "mainModel.bukrs"
        },
        {
          "title": "",
          "component": "hidden",
          "name": "mainModel.userid"
        },
        {
          "title": "",
          "component": "hidden",
          "name": "mainModel.username"
        },
        {
          "title": "",
          "component": "hidden",
          "name": "mainModel.pernr"
        },
        {
          "title": "",
          "component": "hidden",
          "name": "mainModel.syspostname"
        },
        {
          "title": "",
          "component": "hidden",
          "name": "mainModel.sysdeptid"
        },
        {
          "title": "",
          "component": "hidden",
          "name": "mainModel.sysdeptname"
        },
        {
          "title": "",
          "component": "hidden",
          "name": "mainModel.sysbusinessunitid"
        },
        {
          "title": "",
          "component": "hidden",
          "name": "mainModel.sysbusinessunitname"
        },
        {
          "title": "",
          "component": "hidden",
          "name": "mainModel.postid"
        },
        {
          "title": "",
          "component": "hidden",
          "name": "mainModel.id"
        }
      ]
    },
    {
			"title": "录用列表",
			"pageid": "xtlylb",
			"component": "panel",
			"subComponents": [
				{
					"title": "",
					"component": "table_form",
					"titleIndex": 0,
					"basePath": "staffemploysubapplist",
					"id": "LA_xtrecruit",
					"tableForms": [
				{
					"title": "录用人姓名",
					"component": "text",
					"id": "s_username",
					"editablenode": "",
					"name": "s_username"
				},
				{
					"title": "性别",
					"component": "text",
					"id": "s_sex",
					"editablenode": "",
					"name": "s_sex"
				},
				{
					"title": "学历",
					"component": "text",
					"id": "s_edu",
					"editablenode": "",
					"name": "s_edu"
				},
				{
					"title": "毕业学校",
					"component": "text",
					"id": "s_school",
					"editablenode": "",
					"name": "s_school"
				},
				{
					"title": "专业",
					"component": "text",
					"id": "s_zhuanye",
					"editablenode": "",
					"name": "s_zhuanye"
				},
				{
					"title": "身份证号",
					"component": "text",
					"id": "s_code",
					"editablenode": "",
					"name": "s_code"
				},{
                        "title": "所属公司",
                        "component": "text",
                        "id": "s_bukrtxt",
                        "editablenode": "",
                        "name": "s_bukrtxt"
                      },{
                        "title": "所属部门",
                        "component": "text",
                        "id": "s_deptnm",
                        "editablenode": "",
                        "name": "s_deptnm"
                      },{
                        "title": "岗位名称",
                        "component": "text",
                        "id": "s_postnm",
                        "editablenode": "",
                        "name": "s_postnm"
                      },{
                        "title": "岗位等级",
                        "component": "text",
                        "id": "s_postlevel",
                        "editablenode": "",
                        "name": "s_postlevel"
                      }

					]
				}
			]
		}
  ],
  "refers": {
  }
}
